{
  "generated_at": "2026-07-15 11:50:40 Asia/Taipei",
  "data_date": "2026-07-15",
  "timezone": "Asia/Taipei",
  "status": "ok",
  "source": "Google News RSS theme classifier; market data pipeline pending",
  "records": [
    {
      "theme_key": "ai",
      "title": "AI 與半導體供應鏈",
      "summary": "AI 與半導體供應鏈出現 8 則相關訊號，重點新聞包含：蘋果正在與新創公司洽談縮小人工智慧模型以在 iPhone 上運行；英特爾、AMD 傳統 CPU 出現在新 PC 中，因為它們優先考慮伺服器市場：Susquehanna",
      "impact": "直接影響 AI 伺服器、晶圓代工、散熱、電源與高速傳輸供應鏈，需用月營收與法人籌碼驗證。",
      "watch": "觀察台積電、AI 伺服器、散熱、電源與 PCB 族群是否量價同步，並確認月營收是否加速。",
      "count": 8
    },
    {
      "theme_key": "rates",
      "title": "利率、通膨與估值",
      "summary": "利率、通膨與估值出現 6 則相關訊號，重點新聞包含：股市因通膨和銀行業績疲軟而上漲，而石油因美伊敵對行動而上漲；華倫呼籲調查聯準會對矽谷銀行失敗的外部審查",
      "impact": "利率變化會改變高估值成長股折現率，也影響金融、債券與美元方向。",
      "watch": "觀察美債 10Y、FedWatch、美元指數與高估值科技股的同向或背離。",
      "count": 6
    },
    {
      "theme_key": "markets",
      "title": "全球股市與風險情緒",
      "summary": "全球股市與風險情緒出現 2 則相關訊號，重點新聞包含：解釋者－檢察官可以強迫《紐約時報》記者在洩密調查中作證嗎？；英國博彩公司經受住了一場棘手的世界杯",
      "impact": "全球市場風險情緒會決定資金是否願意承接成長股與高本益比族群。",
      "watch": "觀察 VIX、Nasdaq、SOX、S&P 500 與台股電子成交比重。",
      "count": 2
    }
  ]
}